README.md
abi_fetcher/README.md
abi_fetcher/__init__.py
abi_fetcher/abi_fetcher.py
abi_fetcher/chainlist.json
abi_fetcher/client.py
abi_fetcher-0.1.1.dist-info/LICENSE
abi_fetcher-0.1.1.dist-info/METADATA
abi_fetcher-0.1.1.dist-info/WHEEL
abi_fetcher-0.1.1.dist-info/entry_points.txt
abi_fetcher-0.1.1.dist-info/top_level.txt
abi_fetcher-0.1.1.dist-info/RECORD
