Metadata-Version: 2.2
Name: abi-fetcher
Version: 0.1.1
Summary: A Python package to fetch smart contract ABIs from all EVM compatible blockchains
Home-page: https://github.com/zorglob21/ABI_fetcher
Author: Yann Neve
Author-email: yann.nx321.subprime216@simplelogin.com
Classifier: Programming Language :: Python :: 3
Classifier: License :: OSI Approved :: Apache Software License
Classifier: Operating System :: OS Independent
Requires-Python: >=3.7
License-File: LICENSE
Requires-Dist: requests
Dynamic: author
Dynamic: author-email
Dynamic: classifier
Dynamic: description
Dynamic: description-content-type
Dynamic: home-page
Dynamic: requires-dist
Dynamic: requires-python
Dynamic: summary
